{
  "unversionedId": "speakers",
  "id": "speakers",
  "title": "Speakers",
  "description": "To be announced soon!",
  "source": "@site/docs/speakers.md",
  "sourceDirName": ".",
  "slug": "/speakers",
  "permalink": "/docs/speakers",
  "editUrl": "https://github.com/madices/madices.github.io/edit/master/docs/speakers.md",
  "tags": [],
  "version": "current",
  "lastUpdatedAt": 1539502055,
  "formattedLastUpdatedAt": "10/14/2018",
  "frontMatter": {
    "title": "Speakers",
    "sidebar_label": "Speakers"
  }
}